tencentcloud/__init__.py
tencentcloud/iai/__init__.py
tencentcloud/iai/v20180301/__init__.py
tencentcloud/iai/v20180301/errorcodes.py
tencentcloud/iai/v20180301/iai_client.py
tencentcloud/iai/v20180301/iai_client_async.py
tencentcloud/iai/v20180301/models.py
tencentcloud/iai/v20200303/__init__.py
tencentcloud/iai/v20200303/errorcodes.py
tencentcloud/iai/v20200303/iai_client.py
tencentcloud/iai/v20200303/iai_client_async.py
tencentcloud/iai/v20200303/models.py
tencentcloud_sdk_python_iai-3.1.25.dist-info/METADATA
tencentcloud_sdk_python_iai-3.1.25.dist-info/WHEEL
tencentcloud_sdk_python_iai-3.1.25.dist-info/top_level.txt
tencentcloud_sdk_python_iai-3.1.25.dist-info/RECORD
